xpathparser/__init__.py
xpath_parser-0.0.1.dist-info/LICENSE
xpath_parser-0.0.1.dist-info/METADATA
xpath_parser-0.0.1.dist-info/WHEEL
xpath_parser-0.0.1.dist-info/top_level.txt
xpath_parser-0.0.1.dist-info/RECORD
