Metadata-Version: 2.1
Name: xpath-parser
Version: 0.0.1
Summary: A xpath expression parser
Home-page: https://github.com/dytttf/xpath-parser
Author: dytttf
Author-email: 1821367759@qq.com
License: UNKNOWN
Platform: UNKNOWN
Classifier: Programming Language :: Python :: 3
Classifier: License :: OSI Approved :: MIT License
Classifier: Operating System :: OS Independent
